isoqmap/__init__.py
isoqmap/config.ini
isoqmap/main.py
isoqmap/setup.py
isoqmap/commands/__init__.py
isoqmap/commands/download.py
isoqmap/commands/isoquan copy.py
isoqmap/commands/isoquan.py
isoqmap/commands/isoqtl/__init__.py
isoqmap/commands/isoqtl/call.py
isoqmap/commands/isoqtl/format.py
isoqmap/commands/isoqtl/pipeline.py
isoqmap/commands/isoqtl/preprocess.py
isoqmap/resources/__init__.py
isoqmap/resources/XAEM/__init__.py
isoqmap/resources/XAEM/XAEM-binary-0.1.1-cq/R/AEM_update_X_beta.R
isoqmap/resources/XAEM/XAEM-binary-0.1.1-cq/R/Create_count_matrix.R
isoqmap/resources/XAEM/XAEM-binary-0.1.1-cq/R/Rsource.R
isoqmap/resources/XAEM/XAEM-binary-0.1.1-cq/R/buildCRP.R
isoqmap/resources/XAEM/XAEM-binary-0.1.1-cq/R/genPolyesterSimulation.R
isoqmap/resources/XAEM/XAEM-binary-0.1.1-cq/bin/GenTC
isoqmap/resources/XAEM/XAEM-binary-0.1.1-cq/bin/TxIndexer
isoqmap/resources/XAEM/XAEM-binary-0.1.1-cq/bin/XAEM
isoqmap/resources/XAEM/XAEM-binary-0.1.1-cq/lib/libgcc_s.so.1
isoqmap/resources/XAEM/XAEM-binary-0.1.1-cq/lib/libgomp.so.1
isoqmap/resources/XAEM/XAEM-binary-0.1.1-cq/lib/libm.so.6
isoqmap/resources/XAEM/XAEM-binary-0.1.1-cq/lib/librt.so.1.bk
isoqmap/resources/XAEM/XAEM-binary-0.1.1-cq/lib/librt.so.1_glibc_2.36
isoqmap/resources/XAEM/XAEM-binary-0.1.1-cq/lib/libsailfish_core.a
isoqmap/resources/XAEM/XAEM-binary-0.1.1-cq/lib/libtbb.so
isoqmap/resources/XAEM/XAEM-binary-0.1.1-cq/lib/libtbb.so.2
isoqmap/resources/XAEM/XAEM-binary-0.1.1-cq/lib/libtbbmalloc.so
isoqmap/resources/XAEM/XAEM-binary-0.1.1-cq/lib/libtbbmalloc.so.2
isoqmap/resources/XAEM/XAEM-binary-0.1.1-cq/lib/libtbbmalloc_proxy.so
isoqmap/resources/XAEM/XAEM-binary-0.1.1-cq/lib/libtbbmalloc_proxy.so.2
isoqmap/tools/common.py
isoqmap/tools/downloader.py
isoqmap/tools/isoform_rdata2exp.R
isoqmap/tools/pathfinder.py
isoqmap-0.1.6.dist-info/licenses/LICENSE
isoqmap-0.1.6.dist-info/METADATA
isoqmap-0.1.6.dist-info/WHEEL
isoqmap-0.1.6.dist-info/entry_points.txt
isoqmap-0.1.6.dist-info/top_level.txt
isoqmap-0.1.6.dist-info/RECORD
