Metadata-Version: 2.4
Name: isoqmap
Version: 0.1.6
Summary: IsoQMap CLI tool
Author: Chenqing Zheng
License-File: LICENSE
Requires-Dist: click
Requires-Dist: pandas
Requires-Dist: requests
Requires-Dist: scipy
Requires-Dist: statsmodels
Dynamic: license-file
